Metadata-Version: 2.1
Name: blackfox-restapi
Version: 6.1.1
Summary: BlackFox rest api client
Home-page: https://github.com/vodena/BlackFoxRestApiPython
Author: Vodena
Author-email: UNKNOWN
License: UNKNOWN
Keywords: BlackFox
Platform: UNKNOWN
Requires-Dist: certifi (>=2017.4.17)
Requires-Dist: python-dateutil (>=2.1)
Requires-Dist: six (>=1.10)
Requires-Dist: urllib3 (>=1.23)
